clack-1.2.0.dist-info/METADATA
clack-1.2.0.dist-info/DESCRIPTION.rst
clack-1.2.0.dist-info/top_level.txt
clack-1.2.0.dist-info/WHEEL
clack-1.2.0.dist-info/RECORD
clack-1.2.0.dist-info/entry_points.txt
clack-1.2.0.dist-info/metadata.json
clack/schema.json
clack/__init__.py
clack/cli.py
clack/configuration.py
clack/utils.py
