Metadata-Version: 1.1
Name: clack
Version: 1.2.0
Summary: Run multiple iterations of commands from a config file
Home-page: https://github.com/borntyping/clack
Author: Sam Clements
Author-email: sam@borntyping.co.uk
License: MIT
Platform: UNKNOWN
Classifier: Development Status :: 1 - Planning
Classifier: License :: OSI Approved
Classifier: License :: OSI Approved :: MIT License
Classifier: Operating System :: Unix
Classifier: Programming Language :: Python
Classifier: Programming Language :: Python :: 2
Classifier: Programming Language :: Python :: 2.6
Classifier: Programming Language :: Python :: 2.7
Classifier: Programming Language :: Python :: 3
Classifier: Programming Language :: Python :: 3.4
Classifier: Topic :: Software Development :: Libraries
